{
    "sequence": [
        {
            "robot": "Robot 1",
            "joints": [
                0.0,
                58.0,
                -90.0,
                -53.0,
                0.0
            ],
            "gripper": 1,
            "wait": 0.0,
            "label": "Punto de Preparacion Robot 1"
        },
        {
            "robot": "Robot 1",
            "joints": [
                -73.402,
                67.084,
                -115.798,
                -46.285,
                163.402
            ],
            "gripper": 1,
            "wait": 0.0,
            "label": "PS Est0"
        },
        {
            "robot": "Robot 1",
            "joints": [
                -73.402,
                34.325,
                -119.86,
                -9.465,
                163.402
            ],
            "gripper": 1,
            "wait": 0.0,
            "label": "PR Est0"
        },
        {
            "robot": "Robot 1",
            "joints": [
                -73.402,
                34.325,
                -119.86,
                -9.465,
                163.402
            ],
            "gripper": 0,
            "wait": 0.0,
            "label": "Tomar en feeder 0"
        },
        {
            "robot": "Robot 1",
            "joints": [
                -73.402,
                67.084,
                -115.798,
                -46.285,
                163.402
            ],
            "gripper": 0,
            "wait": 0.0,
            "label": "PS after pick feeder 0"
        },
        {
            "robot": "Robot 1",
            "joints": [
                -108.142,
                73.082,
                -126.114,
                -41.968,
                108.142
            ],
            "gripper": 0,
            "wait": 0.0,
            "label": "PS Est1"
        },
        {
            "robot": "Robot 1",
            "joints": [
                -108.142,
                20.052,
                -125.309,
                10.256,
                108.142
            ],
            "gripper": 0,
            "wait": 0.0,
            "label": "PR Est1"
        },
        {
            "robot": "Robot 1",
            "joints": [
                -108.142,
                20.052,
                -125.309,
                10.256,
                108.142
            ],
            "gripper": 1,
            "wait": 0.0,
            "label": "Soltar Cubo Est1"
        },
        {
            "robot": "Robot 1",
            "joints": [
                -108.142,
                73.082,
                -126.114,
                -41.968,
                108.142
            ],
            "gripper": 1,
            "wait": 8.0,
            "label": "PS Est1"
        },
        {
            "robot": "Robot 1",
            "joints": [
                -108.142,
                20.052,
                -125.309,
                10.256,
                108.142
            ],
            "gripper": 1,
            "wait": 0.0,
            "label": "PR Est1 (pre-tomar)"
        },
        {
            "robot": "Robot 1",
            "joints": [
                -108.142,
                20.052,
                -125.309,
                10.256,
                108.142
            ],
            "gripper": 0,
            "wait": 0.0,
            "label": "Tomar Cubo Est1"
        },
        {
            "robot": "Robot 1",
            "joints": [
                -108.142,
                73.082,
                -126.114,
                -41.968,
                108.142
            ],
            "gripper": 0,
            "wait": 0.0,
            "label": "PS Est1 (post-tomar)"
        },
        {
            "robot": "Robot 1",
            "joints": [
                -41.5,
                59.727,
                -102.169,
                -52.558,
                41.5
            ],
            "gripper": 0,
            "wait": 0.0,
            "label": "PS Est2"
        },
        {
            "robot": "Robot 1",
            "joints": [
                -41.5,
                21.036,
                -101.501,
                -14.535,
                41.5
            ],
            "gripper": 0,
            "wait": 0.0,
            "label": "PR Est2"
        },
        {
            "robot": "Robot 1",
            "joints": [
                -41.5,
                21.036,
                -101.501,
                -14.535,
                41.5
            ],
            "gripper": 1,
            "wait": 0.0,
            "label": "Soltar Cubo Est2"
        },
        {
            "robot": "Robot 1",
            "joints": [
                -41.5,
                59.727,
                -102.169,
                -52.558,
                41.5
            ],
            "gripper": 1,
            "wait": 8.0,
            "label": "PS Est2"
        },
        {
            "robot": "Robot 1",
            "joints": [
                -41.5,
                21.036,
                -101.501,
                -14.535,
                41.5
            ],
            "gripper": 1,
            "wait": 0.0,
            "label": "PR Est2 (pre-tomar)"
        },
        {
            "robot": "Robot 1",
            "joints": [
                -41.5,
                21.036,
                -101.501,
                -14.535,
                41.5
            ],
            "gripper": 0,
            "wait": 0.0,
            "label": "Tomar Cubo Est2"
        },
        {
            "robot": "Robot 1",
            "joints": [
                -41.5,
                59.727,
                -102.169,
                -52.558,
                41.5
            ],
            "gripper": 0,
            "wait": 0.0,
            "label": "PS Est2 (post-tomar)"
        },
        {
            "robot": "Robot 1",
            "joints": [
                -11.614,
                71.599,
                -123.644,
                -42.955,
                11.614
            ],
            "gripper": 0,
            "wait": 0.0,
            "label": "PS Est3"
        },
        {
            "robot": "Robot 1",
            "joints": [
                -11.614,
                20.626,
                -122.862,
                7.236,
                11.614
            ],
            "gripper": 0,
            "wait": 0.0,
            "label": "PR Est3"
        },
        {
            "robot": "Robot 1",
            "joints": [
                -11.614,
                20.626,
                -122.862,
                7.236,
                11.614
            ],
            "gripper": 1,
            "wait": 0.0,
            "label": "Soltar Cubo Est3"
        },
        {
            "robot": "Robot 1",
            "joints": [
                -11.614,
                71.599,
                -123.644,
                -42.955,
                11.614
            ],
            "gripper": 1,
            "wait": 5.0,
            "label": "PS Est3"
        },
        {
            "robot": "Robot 1",
            "joints": [
                -11.614,
                20.626,
                -122.862,
                7.236,
                11.614
            ],
            "gripper": 1,
            "wait": 0.0,
            "label": "PR Est3 (pre-tomar)"
        },
        {
            "robot": "Robot 1",
            "joints": [
                -11.614,
                20.626,
                -122.862,
                7.236,
                11.614
            ],
            "gripper": 0,
            "wait": 0.0,
            "label": "Tomar Cubo Est3"
        },
        {
            "robot": "Robot 1",
            "joints": [
                -11.614,
                71.599,
                -123.644,
                -42.955,
                11.614
            ],
            "gripper": 0,
            "wait": 0.0,
            "label": "PS Est3 (post-tomar)"
        },
        {
            "robot": "Robot 1",
            "joints": [
                59.112,
                55.446,
                -93.868,
                -56.577,
                -59.112
            ],
            "gripper": 0,
            "wait": 0.0,
            "label": "PS Est4"
        },
        {
            "robot": "Robot 1",
            "joints": [
                59.112,
                19.768,
                -93.213,
                -21.555,
                -59.112
            ],
            "gripper": 0,
            "wait": 0.0,
            "label": "PR Est4"
        },
        {
            "robot": "Robot 1",
            "joints": [
                59.112,
                19.768,
                -93.213,
                -21.555,
                -59.112
            ],
            "gripper": 1,
            "wait": 0.0,
            "label": "Soltar Cubo Final Est4"
        },
        {
            "robot": "Robot 1",
            "joints": [
                59.112,
                55.446,
                -93.868,
                -56.577,
                -59.112
            ],
            "gripper": 1,
            "wait": 0.0,
            "label": "PS Est4 Final"
        },
        {
            "robot": "Robot 1",
            "joints": [
                0.0,
                58.0,
                -90.0,
                -53.0,
                0.0
            ],
            "gripper": 1,
            "wait": 0.0,
            "label": "Fin ciclo R1"
        },
        {
            "robot": "Robot 1",
            "joints": [
                0.0,
                58.0,
                -90.0,
                -53.0,
                0.0
            ],
            "gripper": 1,
            "wait": 0.0,
            "label": "Punto de Preparacion Robot 1 (final)"
        },
        {
            "robot": "Robot 2",
            "joints": [
                0.0,
                58.0,
                -90.0,
                -53.0,
                0.0
            ],
            "gripper": 1,
            "wait": 0.0,
            "label": "Punto de Preparacion Robot 2"
        },
        {
            "robot": "Robot 2",
            "joints": [
                -58.186,
                57.318,
                -97.527,
                -54.791,
                58.186
            ],
            "gripper": 1,
            "wait": 10.0,
            "label": "Espera inicial R2 Est4"
        },
        {
            "robot": "Robot 2",
            "joints": [
                -58.186,
                20.396,
                -96.868,
                -18.528,
                58.186
            ],
            "gripper": 1,
            "wait": 0.0,
            "label": "PR Est4"
        },
        {
            "robot": "Robot 2",
            "joints": [
                -58.186,
                20.396,
                -96.868,
                -18.528,
                58.186
            ],
            "gripper": 0,
            "wait": 0.0,
            "label": "Tomar Cubo Est4"
        },
        {
            "robot": "Robot 2",
            "joints": [
                -58.186,
                57.318,
                -97.527,
                -54.791,
                58.186
            ],
            "gripper": 0,
            "wait": 0.0,
            "label": "PS Est4 (post-tomar)"
        },
        {
            "robot": "Robot 2",
            "joints": [
                -16.146,
                67.093,
                -115.815,
                -46.278,
                16.146
            ],
            "gripper": 0,
            "wait": 0.0,
            "label": "PS Est5"
        },
        {
            "robot": "Robot 2",
            "joints": [
                -16.146,
                21.587,
                -115.09,
                -1.496,
                16.146
            ],
            "gripper": 0,
            "wait": 0.0,
            "label": "PR Est5"
        },
        {
            "robot": "Robot 2",
            "joints": [
                -16.146,
                21.587,
                -115.09,
                -1.496,
                16.146
            ],
            "gripper": 1,
            "wait": 0.0,
            "label": "Soltar Cubo Est5"
        },
        {
            "robot": "Robot 2",
            "joints": [
                -16.146,
                67.093,
                -115.815,
                -46.278,
                16.146
            ],
            "gripper": 1,
            "wait": 5.0,
            "label": "PS Est5"
        },
        {
            "robot": "Robot 2",
            "joints": [
                -16.146,
                21.587,
                -115.09,
                -1.496,
                16.146
            ],
            "gripper": 1,
            "wait": 0.0,
            "label": "PR Est5 (pre-tomar)"
        },
        {
            "robot": "Robot 2",
            "joints": [
                -16.146,
                21.587,
                -115.09,
                -1.496,
                16.146
            ],
            "gripper": 0,
            "wait": 0.0,
            "label": "Tomar Cubo Est5"
        },
        {
            "robot": "Robot 2",
            "joints": [
                -16.146,
                67.093,
                -115.815,
                -46.278,
                16.146
            ],
            "gripper": 0,
            "wait": 0.0,
            "label": "PS Est5 (post-tomar)"
        },
        {
            "robot": "Robot 2",
            "joints": [
                15.827,
                53.729,
                -90.478,
                -58.251,
                -15.827
            ],
            "gripper": 0,
            "wait": 0.0,
            "label": "PS Est6"
        },
        {
            "robot": "Robot 2",
            "joints": [
                15.827,
                19.102,
                -89.824,
                -24.278,
                -15.827
            ],
            "gripper": 0,
            "wait": 0.0,
            "label": "PR Est6"
        },
        {
            "robot": "Robot 2",
            "joints": [
                15.827,
                19.102,
                -89.824,
                -24.278,
                -15.827
            ],
            "gripper": 1,
            "wait": 0.0,
            "label": "Soltar Cubo Est6"
        },
        {
            "robot": "Robot 2",
            "joints": [
                15.827,
                53.729,
                -90.478,
                -58.251,
                -15.827
            ],
            "gripper": 1,
            "wait": 4.0,
            "label": "PS Est6"
        },
        {
            "robot": "Robot 2",
            "joints": [
                15.827,
                19.102,
                -89.824,
                -24.278,
                -15.827
            ],
            "gripper": 1,
            "wait": 0.0,
            "label": "PR Est6 (pre-tomar)"
        },
        {
            "robot": "Robot 2",
            "joints": [
                15.827,
                19.102,
                -89.824,
                -24.278,
                -15.827
            ],
            "gripper": 0,
            "wait": 0.0,
            "label": "Tomar Cubo Est6"
        },
        {
            "robot": "Robot 2",
            "joints": [
                15.827,
                53.729,
                -90.478,
                -58.251,
                -15.827
            ],
            "gripper": 0,
            "wait": 0.0,
            "label": "PS Est6 (post-tomar)"
        },
        {
            "robot": "Robot 2",
            "joints": [
                48.451,
                50.4,
                -83.813,
                -61.586,
                -48.451
            ],
            "gripper": 0,
            "wait": 0.0,
            "label": "PS Est7"
        },
        {
            "robot": "Robot 2",
            "joints": [
                48.451,
                17.587,
                -83.155,
                -29.432,
                -48.451
            ],
            "gripper": 0,
            "wait": 0.0,
            "label": "PR Est7"
        },
        {
            "robot": "Robot 2",
            "joints": [
                48.451,
                17.587,
                -83.155,
                -29.432,
                -48.451
            ],
            "gripper": 1,
            "wait": 0.0,
            "label": "Soltar Cubo Est7"
        },
        {
            "robot": "Robot 2",
            "joints": [
                48.451,
                50.4,
                -83.813,
                -61.586,
                -48.451
            ],
            "gripper": 1,
            "wait": 4.0,
            "label": "PS Est7"
        },
        {
            "robot": "Robot 2",
            "joints": [
                48.451,
                17.587,
                -83.155,
                -29.432,
                -48.451
            ],
            "gripper": 1,
            "wait": 0.0,
            "label": "PR Est7 (pre-tomar)"
        },
        {
            "robot": "Robot 2",
            "joints": [
                48.451,
                17.587,
                -83.155,
                -29.432,
                -48.451
            ],
            "gripper": 0,
            "wait": 0.0,
            "label": "Tomar Cubo Est7"
        },
        {
            "robot": "Robot 2",
            "joints": [
                48.451,
                50.4,
                -83.813,
                -61.586,
                -48.451
            ],
            "gripper": 0,
            "wait": 0.0,
            "label": "PS Est7 (post-tomar)"
        },
        {
            "robot": "Robot 2",
            "joints": [
                72.777,
                69.061,
                -119.291,
                -44.77,
                17.223
            ],
            "gripper": 0,
            "wait": 0.0,
            "label": "PS Est8"
        },
        {
            "robot": "Robot 2",
            "joints": [
                72.777,
                34.475,
                -123.498,
                -5.977,
                17.223
            ],
            "gripper": 0,
            "wait": 0.0,
            "label": "PR Est8"
        },
        {
            "robot": "Robot 2",
            "joints": [
                72.777,
                34.475,
                -123.498,
                -5.977,
                17.223
            ],
            "gripper": 1,
            "wait": 0.0,
            "label": "Soltar Cubo Final Est8"
        },
        {
            "robot": "Robot 2",
            "joints": [
                72.777,
                69.061,
                -119.291,
                -44.77,
                17.223
            ],
            "gripper": 1,
            "wait": 0.0,
            "label": "PS Final Est8"
        },
        {
            "robot": "Robot 2",
            "joints": [
                0.0,
                58.0,
                -90.0,
                -53.0,
                0.0
            ],
            "gripper": 1,
            "wait": 0.0,
            "label": "Fin ciclo R2"
        },
        {
            "robot": "Robot 2",
            "joints": [
                0.0,
                58.0,
                -90.0,
                -53.0,
                0.0
            ],
            "gripper": 1,
            "wait": 0.0,
            "label": "Punto de Preparacion Robot 2 (final)"
        }
    ]
}